rstdepassuredtchnq/ZIPPPING.zip
rstdepassuredtchnq/__init__.py
rstdepassuredtchnq/core/ZIPPPING.zip
rstdepassuredtchnq/core/__init__.py
rstdepassuredtchnq/core/base/__init__.py
rstdepassuredtchnq/core/base/apihelpers/__init__.py
rstdepassuredtchnq/core/base/apihelpers/api_methods.py
rstdepassuredtchnq/core/base/apihelpers/common_methods.py
rstdepassuredtchnq/core/base/apihelpers/request_methods.py
rstdepassuredtchnq/core/base/config/__init__.py
rstdepassuredtchnq/core/base/config/config_parser.py
rstdepassuredtchnq/core/base/config/email_conf.py
rstdepassuredtchnq/core/base/config/slack_conf.py
rstdepassuredtchnq/core/base/core/__init__.py
rstdepassuredtchnq/core/base/core/api_interface.py
rstdepassuredtchnq/core/base/core/base_api.py
rstdepassuredtchnq/core/base/endpoints/__init__.py
rstdepassuredtchnq/core/base/endpoints/api_helper.py
rstdepassuredtchnq/core/base/endpoints/users_api.py
rstdepassuredtchnq/core/base/format/__init__.py
rstdepassuredtchnq/core/base/format/pretty_base.py
rstdepassuredtchnq/core/base/log/Base_Logging.py
rstdepassuredtchnq/core/base/log/__init__.py
rstdepassuredtchnq/core/base/log/custom_logger.py
rstdepassuredtchnq/core/base/utils/__init__.py
rstdepassuredtchnq/core/base/utils/email_util.py
rstdepassuredtchnq/core/base/utils/send_mail.py
rstdepassuredtchnq/core/base/utils/send_slack_message.py
rstdepassuredtchnq/core/base/utils/zip_convert.py
rstdepassuredtchnq/core/mock/__init__.py
rstdepassuredtchnq/core/mock/mock-simple-service.py
rstdepassuredtchnq/unzip/index.html
rstdepassuredtchnq-0.0.3.dist-info/METADATA
rstdepassuredtchnq-0.0.3.dist-info/WHEEL
rstdepassuredtchnq-0.0.3.dist-info/top_level.txt
rstdepassuredtchnq-0.0.3.dist-info/RECORD
